reliev/__init__.py
reliev/store.py
reliev-0.1.0.dist-info/METADATA
reliev-0.1.0.dist-info/WHEEL
reliev-0.1.0.dist-info/licenses/LICENSE
reliev-0.1.0.dist-info/RECORD
