Metadata-Version: 2.4
Name: reliev
Version: 0.1.0
Summary: Complementary store library for observ
Project-URL: Homepage, https://github.com/fork-tongue/reliev
Author-email: Berend Klein Haneveld <berendkleinhaneveld@gmail.com>, Korijn van Golen <korijn@gmail.com>
License-Expression: MIT
License-File: LICENSE
Requires-Python: >=3.9
Requires-Dist: observ>=0.16.0
Requires-Dist: patchdiff>=0.3.6
